__init__.py
builder.py
cb_calculator.py
evt_mixer.py
osss_builder.py
sscorr.py
cb_data/__init__.py
cb_data/v1/ETOS_2018.json
cb_data/v4/high_ETOS_2018.json
cb_data/v4/jpsi_MTOS_2018.json
cb_data/v4/psi2_MTOS_2018.json
cb_data/v5/high_nconst_ETOS_2018.json
cb_data/v5/high_nconst_MTOS_2018.json
cb_data/v6/high_nconst_ETOS_2018.json
cb_data/v6/high_nconst_MTOS_2018.json
cb_data/v6/jpsi_nconst_ETOS_2018.json
cb_data/v6/jpsi_nconst_MTOS_2018.json
cb_data/v6/jpsi_yconst_MTOS_2018.json
cb_data/v6/psi2_nconst_ETOS_2018.json
cb_data/v6/psi2_nconst_MTOS_2018.json
cb_data/v7/jpsi_nconst_ETOS_2018.json
cb_data/v7/jpsi_nconst_MTOS_2018.json
cb_data/v7/psi2_nconst_ETOS_2018.json
cb_data/v7/psi2_nconst_MTOS_2018.json
cb_data/v8/high_nconst_ETOS_2018.json
cb_data/v8/high_nconst_MTOS_2018.json
cb_data/v9/high_nconst_ETOS_all.json
cb_data/v9/high_nconst_GTIS_all.json
cb_data/v9/high_nconst_MTOS_all.json
cb_pars/__init__.py
cb_pars/v1/hypexp.json
cb_pars/v1/sujohnson.json
rx_combinatorial-0.1.2.data/scripts/cb_job
rx_combinatorial-0.1.2.data/scripts/cb_submit
rx_combinatorial-0.1.2.data/scripts/get_cb_data
rx_combinatorial-0.1.2.data/scripts/get_scales
rx_combinatorial-0.1.2.data/scripts/plot_data
rx_combinatorial-0.1.2.data/scripts/plot_uncertainties
rx_combinatorial-0.1.2.dist-info/METADATA
rx_combinatorial-0.1.2.dist-info/WHEEL
rx_combinatorial-0.1.2.dist-info/top_level.txt
rx_combinatorial-0.1.2.dist-info/RECORD
