Metadata-Version: 2.1
Name: rx_combinatorial
Version: 0.1.2
Summary: Project used to calculate combinatorial background shapes
Requires-Dist: pandas
Requires-Dist: mplhep
Requires-Dist: rx-scripts >=0.2.7
Requires-Dist: rx-tools >=0.0.3
Requires-Dist: rx-selection >=0.0.2
Requires-Dist: logzero
Requires-Dist: matplotlib
Requires-Dist: hep-ml
Requires-Dist: zfit >=0.14.0
